{"name":"Registro exitoso de un nuevo usuario","id":"como-gerente-de-la-empresa-yaelcoronel;registro-exitoso-de-un-nuevo-usuario","testSteps":[{"number":1,"description":"Given Estoy en la pagina de inicio de sesion","duration":34,"startTime":"2024-06-26T12:02:43.785-06:00[America/Mexico_City]","result":"PENDING","precondition":false,"level":0},{"number":2,"description":"When Hago click en el boton de registrar","duration":3,"startTime":"2024-06-26T12:02:43.822-06:00[America/Mexico_City]","result":"IGNORED","precondition":false,"level":0},{"number":3,"description":"And Ingreso los datos del registro","duration":1,"startTime":"2024-06-26T12:02:43.826-06:00[America/Mexico_City]","result":"IGNORED","precondition":false,"level":0},{"number":4,"description":"Then Envio el formulario de registro de usuarios","duration":2,"startTime":"2024-06-26T12:02:43.828-06:00[America/Mexico_City]","result":"IGNORED","precondition":false,"level":0}],"userStory":{"id":"como-gerente-de-la-empresa-yaelcoronel","storyName":"Como gerente de la empresa yaelcoronel","displayName":"Como gerente de la empresa yaelcoronel","path":"RegistroDeUsuarios.feature","narrative":"    Necesito ver una funcionalidad de registro de usuarios en la pagina\n    Para darle acceso a la plataforma de administracion a mis clientes mayoristas","type":"feature","qualifiedTag":{"name":"Como gerente de la empresa yaelcoronel","type":"feature","displayName":"Como gerente de la empresa yaelcoronel"}},"featureTag":{"name":"Como gerente de la empresa yaelcoronel","type":"feature","displayName":"Como gerente de la empresa yaelcoronel"},"title":"Registro exitoso de un nuevo usuario","description":"","tags":[{"name":"test1","type":"tag","displayName":"test1"},{"name":"Windows","type":"context","displayName":"Windows"},{"name":"Como gerente de la empresa yaelcoronel","type":"feature","displayName":"Como gerente de la empresa yaelcoronel"}],"allTags":[{"name":"test1","type":"tag","displayName":"test1"},{"name":"Windows","type":"context","displayName":"Windows"},{"name":"Como gerente de la empresa yaelcoronel","type":"feature","displayName":"Como gerente de la empresa yaelcoronel"}],"startTime":"2024-06-26T12:02:43.713-06:00[America/Mexico_City]","duration":121,"projectKey":"","annotatedResult":"PENDING","isManualTestingUpToDate":false,"context":"windows","manual":false,"testSource":"Cucumber","result":"PENDING"}